mtaio/__init__.py
mtaio/exceptions.py
mtaio/typing.py
mtaio/cache/__init__.py
mtaio/cache/distributed.py
mtaio/cache/ttl.py
mtaio/core/__init__.py
mtaio/core/executor.py
mtaio/core/primitives.py
mtaio/data/__init__.py
mtaio/data/observable.py
mtaio/data/pipeline.py
mtaio/data/stream.py
mtaio/decorators/__init__.py
mtaio/decorators/adapters.py
mtaio/decorators/control.py
mtaio/events/__init__.py
mtaio/events/channel.py
mtaio/events/emitter.py
mtaio/logging/__init__.py
mtaio/logging/logger.py
mtaio/monitoring/__init__.py
mtaio/monitoring/monitor.py
mtaio/monitoring/profiler.py
mtaio/optimization/__init__.py
mtaio/optimization/optimizer.py
mtaio/protocols/__init__.py
mtaio/protocols/asgi.py
mtaio/protocols/mail.py
mtaio/protocols/mqtt.py
mtaio/resources/__init__.py
mtaio/resources/limiter.py
mtaio/resources/timeout.py
mtaio-0.1.0.dist-info/LICENSE
mtaio-0.1.0.dist-info/METADATA
mtaio-0.1.0.dist-info/WHEEL
mtaio-0.1.0.dist-info/top_level.txt
mtaio-0.1.0.dist-info/RECORD
