Metadata-Version: 2.1
Name: mtaio
Version: 0.1.0
Summary: A comprehensive framework for asynchronous I/O operations and utilities.
Author: t3tra
Author-email: t3tra <admin@t3ra.net>
License: MIT License
Project-URL: Repository, https://github.com/t3tra-dev/mtaio.git
Project-URL: Issues, https://github.com/t3tra-dev/mtaio/issues
Keywords: python,framework,utilitiy
Classifier: Development Status :: 5 - Production/Stable
Classifier: Intended Audience :: Developers
Classifier: Operating System :: OS Independent
Classifier: Programming Language :: Python
Classifier: Programming Language :: Python :: 3
Classifier: Programming Language :: Python :: 3.11
Classifier: Programming Language :: Python :: 3.12
Classifier: Programming Language :: Python :: 3.13
Classifier: Topic :: Software Development :: Libraries
Classifier: Topic :: Software Development :: Libraries :: Python Modules
Classifier: Topic :: Utilities
Classifier: Typing :: Typed
Classifier: License :: OSI Approved :: MIT License
Classifier: Operating System :: OS Independent
Requires-Python: >=3.11
License-File: LICENSE
